django_orgco-0.1.0.dist-info/pydist.json
django_orgco-0.1.0.dist-info/METADATA
django_orgco-0.1.0.dist-info/WHEEL
django_orgco-0.1.0.dist-info/DESCRIPTION.rst
django_orgco-0.1.0.dist-info/RECORD
django_orgco-0.1.0.dist-info/top_level.txt
django_orgco/__init__.py
django_orgco/templatetags/__init__.py
django_orgco/templatetags/orgdoc.py
