Metadata-Version: 2.0
Name: django-orgco
Version: 0.1.0
Summary: django-orgco implements a template tag to use orgco easily in django templates
Home-page: https://github.com/paetzke/django-orgco
Author: Friedrich Paetzke
Author-email: f.paetzke@gmail.com
License: BSD
Platform: UNKNOWN
Classifier: Framework :: Django
Classifier: Intended Audience :: Developers
Classifier: License :: OSI Approved :: BSD License
Classifier: Operating System :: OS Independent
Classifier: Programming Language :: Python
Classifier: Programming Language :: Python :: 2
Classifier: Programming Language :: Python :: 2.7
Classifier: Programming Language :: Python :: 3
Classifier: Programming Language :: Python :: 3.3
Classifier: Programming Language :: Python :: Implementation :: CPython
Classifier: Programming Language :: Python :: Implementation :: PyPy
Classifier: Topic :: Software Development :: Libraries
Classifier: Topic :: Text Editors :: Emacs
Classifier: Topic :: Text Processing
Classifier: Topic :: Text Processing :: Markup
Requires-Dist: django
Requires-Dist: orgco (>=0.0.11)
